grades/__init__.py
grades/check.py
grades_check-0.0.3.dist-info/LICENCE
grades_check-0.0.3.dist-info/METADATA
grades_check-0.0.3.dist-info/WHEEL
grades_check-0.0.3.dist-info/top_level.txt
grades_check-0.0.3.dist-info/RECORD
