Metadata-Version: 2.1
Name: grades-check
Version: 0.0.3
Summary: A simple script that allows you to verify if a site changed or not
Home-page: UNKNOWN
Author: Ailenei dan
Author-email: ailenei_d1996@yahoo.com
License: UNKNOWN
Platform: UNKNOWN
Classifier: Programming Language :: Python :: 3
Classifier: License :: OSI Approved :: MIT License
Classifier: Operating System :: OS Independent
Requires-Dist: requests
